[
  {
    "frontmatter": {
      "layout": "@/layouts/Layout.astro",
      "title": "AracnaBlob"
    },
    "url": "/core/classes/aracna.blob",
    "file": "/home/dario/Personal/@aracna/website/src/pages/core/classes/aracna.blob.mdx"
  },
  {
    "frontmatter": {
      "layout": "@/layouts/Layout.astro",
      "title": "AracnaFile"
    },
    "url": "/core/classes/aracna.file",
    "file": "/home/dario/Personal/@aracna/website/src/pages/core/classes/aracna.file.mdx"
  },
  {
    "frontmatter": {
      "layout": "@/layouts/Layout.astro",
      "title": "FetchError",
      "draft": true
    },
    "url": "/core/classes/fetch.error",
    "file": "/home/dario/Personal/@aracna/website/src/pages/core/classes/fetch.error.mdx"
  },
  {
    "frontmatter": {
      "layout": "@/layouts/Layout.astro",
      "title": "FetchResponse",
      "draft": true
    },
    "url": "/core/classes/fetch.response",
    "file": "/home/dario/Personal/@aracna/website/src/pages/core/classes/fetch.response.mdx"
  },
  {
    "frontmatter": {
      "layout": "@/layouts/Layout.astro",
      "title": "debounce"
    },
    "url": "/core/functions/debounce",
    "file": "/home/dario/Personal/@aracna/website/src/pages/core/functions/debounce.mdx"
  },
  {
    "frontmatter": {
      "layout": "@/layouts/Layout.astro",
      "title": "gql"
    },
    "url": "/core/functions/gql",
    "file": "/home/dario/Personal/@aracna/website/src/pages/core/functions/gql.mdx"
  },
  {
    "frontmatter": {
      "layout": "@/layouts/Layout.astro",
      "title": "ma"
    },
    "url": "/core/functions/ma",
    "file": "/home/dario/Personal/@aracna/website/src/pages/core/functions/ma.mdx"
  },
  {
    "frontmatter": {
      "layout": "@/layouts/Layout.astro",
      "title": "mtc"
    },
    "url": "/core/functions/mtc",
    "file": "/home/dario/Personal/@aracna/website/src/pages/core/functions/mtc.mdx"
  },
  {
    "frontmatter": {
      "layout": "@/layouts/Layout.astro",
      "title": "mtcp"
    },
    "url": "/core/functions/mtcp",
    "file": "/home/dario/Personal/@aracna/website/src/pages/core/functions/mtcp.mdx"
  },
  {
    "frontmatter": {
      "layout": "@/layouts/Layout.astro",
      "title": "noop"
    },
    "url": "/core/functions/noop",
    "file": "/home/dario/Personal/@aracna/website/src/pages/core/functions/noop.mdx"
  },
  {
    "frontmatter": {
      "layout": "@/layouts/Layout.astro",
      "title": "rc"
    },
    "url": "/core/functions/rc",
    "file": "/home/dario/Personal/@aracna/website/src/pages/core/functions/rc.mdx"
  },
  {
    "frontmatter": {
      "layout": "@/layouts/Layout.astro",
      "title": "rcp"
    },
    "url": "/core/functions/rcp",
    "file": "/home/dario/Personal/@aracna/website/src/pages/core/functions/rcp.mdx"
  },
  {
    "frontmatter": {
      "layout": "@/layouts/Layout.astro",
      "title": "rne"
    },
    "url": "/core/functions/rne",
    "file": "/home/dario/Personal/@aracna/website/src/pages/core/functions/rne.mdx"
  },
  {
    "frontmatter": {
      "layout": "@/layouts/Layout.astro",
      "title": "rv"
    },
    "url": "/core/functions/rv",
    "file": "/home/dario/Personal/@aracna/website/src/pages/core/functions/rv.mdx"
  },
  {
    "frontmatter": {
      "layout": "@/layouts/Layout.astro",
      "title": "sleep"
    },
    "url": "/core/functions/sleep",
    "file": "/home/dario/Personal/@aracna/website/src/pages/core/functions/sleep.mdx"
  },
  {
    "frontmatter": {
      "layout": "@/layouts/Layout.astro",
      "title": "tc"
    },
    "url": "/core/functions/tc",
    "file": "/home/dario/Personal/@aracna/website/src/pages/core/functions/tc.mdx"
  },
  {
    "frontmatter": {
      "layout": "@/layouts/Layout.astro",
      "title": "tcp"
    },
    "url": "/core/functions/tcp",
    "file": "/home/dario/Personal/@aracna/website/src/pages/core/functions/tcp.mdx"
  },
  {
    "frontmatter": {
      "layout": "@/layouts/Layout.astro",
      "title": "throttle"
    },
    "url": "/core/functions/throttle",
    "file": "/home/dario/Personal/@aracna/website/src/pages/core/functions/throttle.mdx"
  },
  {
    "frontmatter": {
      "layout": "@/layouts/Layout.astro",
      "title": "tie"
    },
    "url": "/core/functions/tie",
    "file": "/home/dario/Personal/@aracna/website/src/pages/core/functions/tie.mdx"
  },
  {
    "frontmatter": {
      "layout": "@/layouts/Layout.astro",
      "title": "tne"
    },
    "url": "/core/functions/tne",
    "file": "/home/dario/Personal/@aracna/website/src/pages/core/functions/tne.mdx"
  },
  {
    "frontmatter": {
      "layout": "@/layouts/Layout.astro",
      "title": "wf"
    },
    "url": "/core/functions/wf",
    "file": "/home/dario/Personal/@aracna/website/src/pages/core/functions/wf.mdx"
  },
  {
    "frontmatter": {
      "layout": "@/layouts/Layout.astro",
      "title": "wfp"
    },
    "url": "/core/functions/wfp",
    "file": "/home/dario/Personal/@aracna/website/src/pages/core/functions/wfp.mdx"
  },
  {
    "frontmatter": {
      "layout": "@/layouts/Layout.astro",
      "order": -1,
      "title": "Get Started"
    },
    "url": "/core/get-started",
    "file": "/home/dario/Personal/@aracna/website/src/pages/core/get-started.mdx"
  },
  {
    "frontmatter": {
      "layout": "@/layouts/Layout.astro",
      "title": "API"
    },
    "url": "/core/modules/api",
    "file": "/home/dario/Personal/@aracna/website/src/pages/core/modules/api.mdx"
  },
  {
    "frontmatter": {
      "layout": "@/layouts/Layout.astro",
      "title": "Base16"
    },
    "url": "/core/modules/base16",
    "file": "/home/dario/Personal/@aracna/website/src/pages/core/modules/base16.mdx"
  },
  {
    "frontmatter": {
      "layout": "@/layouts/Layout.astro",
      "title": "Base32"
    },
    "url": "/core/modules/base32",
    "file": "/home/dario/Personal/@aracna/website/src/pages/core/modules/base32.mdx"
  },
  {
    "frontmatter": {
      "layout": "@/layouts/Layout.astro",
      "title": "Base64"
    },
    "url": "/core/modules/base64",
    "file": "/home/dario/Personal/@aracna/website/src/pages/core/modules/base64.mdx"
  },
  {
    "frontmatter": {
      "layout": "@/layouts/Layout.astro",
      "title": "Cookie"
    },
    "url": "/core/modules/cookie",
    "file": "/home/dario/Personal/@aracna/website/src/pages/core/modules/cookie.mdx"
  },
  {
    "frontmatter": {
      "layout": "@/layouts/Layout.astro",
      "title": "DeferredPromise"
    },
    "url": "/core/modules/deferred-promise",
    "file": "/home/dario/Personal/@aracna/website/src/pages/core/modules/deferred-promise.mdx"
  },
  {
    "frontmatter": {
      "layout": "@/layouts/Layout.astro",
      "title": "Environment"
    },
    "url": "/core/modules/environment",
    "file": "/home/dario/Personal/@aracna/website/src/pages/core/modules/environment.mdx"
  },
  {
    "frontmatter": {
      "layout": "@/layouts/Layout.astro",
      "title": "Fetch"
    },
    "url": "/core/modules/fetch",
    "file": "/home/dario/Personal/@aracna/website/src/pages/core/modules/fetch.mdx"
  },
  {
    "frontmatter": {
      "layout": "@/layouts/Layout.astro",
      "title": "GraphQLAPI"
    },
    "url": "/core/modules/graphql-api",
    "file": "/home/dario/Personal/@aracna/website/src/pages/core/modules/graphql-api.mdx"
  },
  {
    "frontmatter": {
      "layout": "@/layouts/Layout.astro",
      "title": "History"
    },
    "url": "/core/modules/history",
    "file": "/home/dario/Personal/@aracna/website/src/pages/core/modules/history.mdx"
  },
  {
    "frontmatter": {
      "layout": "@/layouts/Layout.astro",
      "title": "IDUtils"
    },
    "url": "/core/modules/id",
    "file": "/home/dario/Personal/@aracna/website/src/pages/core/modules/id.mdx"
  },
  {
    "frontmatter": {
      "layout": "@/layouts/Layout.astro",
      "title": "Interval"
    },
    "url": "/core/modules/interval",
    "file": "/home/dario/Personal/@aracna/website/src/pages/core/modules/interval.mdx"
  },
  {
    "frontmatter": {
      "layout": "@/layouts/Layout.astro",
      "title": "Localization"
    },
    "url": "/core/modules/localization",
    "file": "/home/dario/Personal/@aracna/website/src/pages/core/modules/localization.mdx"
  },
  {
    "frontmatter": {
      "layout": "@/layouts/Layout.astro",
      "title": "Logger"
    },
    "url": "/core/modules/logger",
    "file": "/home/dario/Personal/@aracna/website/src/pages/core/modules/logger.mdx"
  },
  {
    "frontmatter": {
      "layout": "@/layouts/Layout.astro",
      "title": "Polyfill"
    },
    "url": "/core/modules/polyfill",
    "file": "/home/dario/Personal/@aracna/website/src/pages/core/modules/polyfill.mdx"
  },
  {
    "frontmatter": {
      "layout": "@/layouts/Layout.astro",
      "title": "Status"
    },
    "url": "/core/modules/status",
    "file": "/home/dario/Personal/@aracna/website/src/pages/core/modules/status.mdx"
  },
  {
    "frontmatter": {
      "layout": "@/layouts/Layout.astro",
      "title": "Storage"
    },
    "url": "/core/modules/storage",
    "file": "/home/dario/Personal/@aracna/website/src/pages/core/modules/storage.mdx"
  },
  {
    "frontmatter": {
      "layout": "@/layouts/Layout.astro",
      "title": "TextCodec"
    },
    "url": "/core/modules/text-codec",
    "file": "/home/dario/Personal/@aracna/website/src/pages/core/modules/text-codec.mdx"
  },
  {
    "frontmatter": {
      "layout": "@/layouts/Layout.astro",
      "title": "Timeout"
    },
    "url": "/core/modules/timeout",
    "file": "/home/dario/Personal/@aracna/website/src/pages/core/modules/timeout.mdx"
  },
  {
    "frontmatter": {
      "layout": "@/layouts/Layout.astro",
      "title": "Array"
    },
    "url": "/core/utils/array",
    "file": "/home/dario/Personal/@aracna/website/src/pages/core/utils/array.mdx"
  },
  {
    "frontmatter": {
      "layout": "@/layouts/Layout.astro",
      "title": "Blob"
    },
    "url": "/core/utils/blob",
    "file": "/home/dario/Personal/@aracna/website/src/pages/core/utils/blob.mdx"
  },
  {
    "frontmatter": {
      "layout": "@/layouts/Layout.astro",
      "title": "Cookie"
    },
    "url": "/core/utils/cookie",
    "file": "/home/dario/Personal/@aracna/website/src/pages/core/utils/cookie.mdx"
  },
  {
    "frontmatter": {
      "layout": "@/layouts/Layout.astro",
      "title": "Date"
    },
    "url": "/core/utils/date",
    "file": "/home/dario/Personal/@aracna/website/src/pages/core/utils/date.mdx"
  },
  {
    "frontmatter": {
      "layout": "@/layouts/Layout.astro",
      "title": "Document"
    },
    "url": "/core/utils/document",
    "file": "/home/dario/Personal/@aracna/website/src/pages/core/utils/document.mdx"
  },
  {
    "frontmatter": {
      "layout": "@/layouts/Layout.astro",
      "title": "Emoji"
    },
    "url": "/core/utils/emoji",
    "file": "/home/dario/Personal/@aracna/website/src/pages/core/utils/emoji.mdx"
  },
  {
    "frontmatter": {
      "layout": "@/layouts/Layout.astro",
      "title": "Error"
    },
    "url": "/core/utils/error",
    "file": "/home/dario/Personal/@aracna/website/src/pages/core/utils/error.mdx"
  },
  {
    "frontmatter": {
      "layout": "@/layouts/Layout.astro",
      "title": "Fetch"
    },
    "url": "/core/utils/fetch",
    "file": "/home/dario/Personal/@aracna/website/src/pages/core/utils/fetch.mdx"
  },
  {
    "frontmatter": {
      "layout": "@/layouts/Layout.astro",
      "title": "File"
    },
    "url": "/core/utils/file",
    "file": "/home/dario/Personal/@aracna/website/src/pages/core/utils/file.mdx"
  },
  {
    "frontmatter": {
      "layout": "@/layouts/Layout.astro",
      "title": "FormData"
    },
    "url": "/core/utils/form-data",
    "file": "/home/dario/Personal/@aracna/website/src/pages/core/utils/form-data.mdx"
  },
  {
    "frontmatter": {
      "layout": "@/layouts/Layout.astro",
      "title": "Function"
    },
    "url": "/core/utils/function",
    "file": "/home/dario/Personal/@aracna/website/src/pages/core/utils/function.mdx"
  },
  {
    "frontmatter": {
      "layout": "@/layouts/Layout.astro",
      "title": "Number"
    },
    "url": "/core/utils/number",
    "file": "/home/dario/Personal/@aracna/website/src/pages/core/utils/number.mdx"
  },
  {
    "frontmatter": {
      "layout": "@/layouts/Layout.astro",
      "title": "Object"
    },
    "url": "/core/utils/object",
    "file": "/home/dario/Personal/@aracna/website/src/pages/core/utils/object.mdx"
  },
  {
    "frontmatter": {
      "layout": "@/layouts/Layout.astro",
      "title": "Promise"
    },
    "url": "/core/utils/promise",
    "file": "/home/dario/Personal/@aracna/website/src/pages/core/utils/promise.mdx"
  },
  {
    "frontmatter": {
      "layout": "@/layouts/Layout.astro",
      "title": "Query Parameters"
    },
    "url": "/core/utils/query-parameters",
    "file": "/home/dario/Personal/@aracna/website/src/pages/core/utils/query-parameters.mdx"
  },
  {
    "frontmatter": {
      "layout": "@/layouts/Layout.astro",
      "title": "String"
    },
    "url": "/core/utils/string",
    "file": "/home/dario/Personal/@aracna/website/src/pages/core/utils/string.mdx"
  },
  {
    "frontmatter": {
      "layout": "@/layouts/Layout.astro",
      "title": "URL"
    },
    "url": "/core/utils/url",
    "file": "/home/dario/Personal/@aracna/website/src/pages/core/utils/url.mdx"
  },
  {
    "frontmatter": {
      "layout": "@/layouts/Layout.astro",
      "order": -1,
      "title": "Introduction"
    },
    "url": "",
    "file": "/home/dario/Personal/@aracna/website/src/pages/index.mdx"
  },
  {
    "frontmatter": {
      "layout": "@/layouts/Layout.astro",
      "title": "autorun"
    },
    "url": "/state-manager/functions/autorun",
    "file": "/home/dario/Personal/@aracna/website/src/pages/state-manager/functions/autorun.mdx"
  },
  {
    "frontmatter": {
      "layout": "@/layouts/Layout.astro",
      "title": "isObservable"
    },
    "url": "/state-manager/functions/is.observable",
    "file": "/home/dario/Personal/@aracna/website/src/pages/state-manager/functions/is.observable.mdx"
  },
  {
    "frontmatter": {
      "layout": "@/layouts/Layout.astro",
      "title": "observe"
    },
    "url": "/state-manager/functions/observe",
    "file": "/home/dario/Personal/@aracna/website/src/pages/state-manager/functions/observe.mdx"
  },
  {
    "frontmatter": {
      "layout": "@/layouts/Layout.astro",
      "title": "reaction"
    },
    "url": "/state-manager/functions/reaction",
    "file": "/home/dario/Personal/@aracna/website/src/pages/state-manager/functions/reaction.mdx"
  },
  {
    "frontmatter": {
      "layout": "@/layouts/Layout.astro",
      "title": "toJS"
    },
    "url": "/state-manager/functions/to.js",
    "file": "/home/dario/Personal/@aracna/website/src/pages/state-manager/functions/to.js.mdx"
  },
  {
    "frontmatter": {
      "layout": "@/layouts/Layout.astro",
      "title": "when"
    },
    "url": "/state-manager/functions/when",
    "file": "/home/dario/Personal/@aracna/website/src/pages/state-manager/functions/when.mdx"
  },
  {
    "frontmatter": {
      "layout": "@/layouts/Layout.astro",
      "order": -1,
      "title": "Get Started"
    },
    "url": "/state-manager/get-started",
    "file": "/home/dario/Personal/@aracna/website/src/pages/state-manager/get-started.mdx"
  },
  {
    "frontmatter": {
      "layout": "@/layouts/Layout.astro",
      "sidebar_position": 2,
      "title": "Get Started"
    },
    "url": "/state-manager/react/get-started",
    "file": "/home/dario/Personal/@aracna/website/src/pages/state-manager/react/get-started.mdx"
  },
  {
    "frontmatter": {
      "layout": "@/layouts/Layout.astro",
      "title": "useAutorun"
    },
    "url": "/state-manager/react/hooks/use-autorun",
    "file": "/home/dario/Personal/@aracna/website/src/pages/state-manager/react/hooks/use-autorun.mdx"
  },
  {
    "frontmatter": {
      "layout": "@/layouts/Layout.astro",
      "title": "useMemoObserver"
    },
    "url": "/state-manager/react/hooks/use-memo-observer",
    "file": "/home/dario/Personal/@aracna/website/src/pages/state-manager/react/hooks/use-memo-observer.mdx"
  },
  {
    "frontmatter": {
      "layout": "@/layouts/Layout.astro",
      "title": "useObservable"
    },
    "url": "/state-manager/react/hooks/use-observable",
    "file": "/home/dario/Personal/@aracna/website/src/pages/state-manager/react/hooks/use-observable.mdx"
  },
  {
    "frontmatter": {
      "layout": "@/layouts/Layout.astro",
      "title": "useObserver"
    },
    "url": "/state-manager/react/hooks/use-observer",
    "file": "/home/dario/Personal/@aracna/website/src/pages/state-manager/react/hooks/use-observer.mdx"
  },
  {
    "frontmatter": {
      "layout": "@/layouts/Layout.astro",
      "title": "useReaction"
    },
    "url": "/state-manager/react/hooks/use-reaction",
    "file": "/home/dario/Personal/@aracna/website/src/pages/state-manager/react/hooks/use-reaction.mdx"
  },
  {
    "frontmatter": {
      "layout": "@/layouts/Layout.astro",
      "title": "useWhen"
    },
    "url": "/state-manager/react/hooks/use-when",
    "file": "/home/dario/Personal/@aracna/website/src/pages/state-manager/react/hooks/use-when.mdx"
  },
  {
    "frontmatter": {
      "layout": "@/layouts/Layout.astro",
      "title": "Avatar"
    },
    "url": "/web/components/data/avatar",
    "file": "/home/dario/Personal/@aracna/website/src/pages/web/components/data/avatar.mdx"
  },
  {
    "frontmatter": {
      "layout": "@/layouts/Layout.astro",
      "order": -1,
      "title": "Get Started"
    },
    "url": "/web/components/get-started",
    "file": "/home/dario/Personal/@aracna/website/src/pages/web/components/get-started.mdx"
  },
  {
    "frontmatter": {
      "layout": "@/layouts/Layout.astro",
      "order": -1,
      "title": "Get Started"
    },
    "url": "/web/get-started",
    "file": "/home/dario/Personal/@aracna/website/src/pages/web/get-started.mdx"
  },
  {
    "frontmatter": {
      "layout": "@/layouts/Layout.astro",
      "title": "LocalStorage"
    },
    "url": "/web/modules/local-storage",
    "file": "/home/dario/Personal/@aracna/website/src/pages/web/modules/local-storage.mdx"
  },
  {
    "frontmatter": {
      "layout": "@/layouts/Layout.astro",
      "title": "SessionStorage"
    },
    "url": "/web/modules/session-storage",
    "file": "/home/dario/Personal/@aracna/website/src/pages/web/modules/session-storage.mdx"
  },
  {
    "frontmatter": {
      "layout": "@/layouts/Layout.astro",
      "title": "WebSocket"
    },
    "url": "/web/modules/web-socket",
    "file": "/home/dario/Personal/@aracna/website/src/pages/web/modules/web-socket.mdx"
  },
  {
    "frontmatter": {
      "layout": "@/layouts/Layout.astro",
      "title": "ImageUtils"
    },
    "url": "/web/utils/image",
    "file": "/home/dario/Personal/@aracna/website/src/pages/web/utils/image.mdx"
  }
]